rogersbank/VERSION
rogersbank/__init__.py
rogersbank/client.py
rogersbank/login.py
rogersbank/secret_provider.py
rogersbank-1.2.0.dist-info/METADATA
rogersbank-1.2.0.dist-info/RECORD
rogersbank-1.2.0.dist-info/WHEEL
rogersbank-1.2.0.dist-info/top_level.txt
